{
	"configurations" : 
	[
		{
			"directories" : 
			[
				{
					"build" : ".",
					"jsonFile" : "directory-.-Debug-f5ebdc15457944623624.json",
					"minimumCMakeVersion" : 
					{
						"string" : "3.10.0"
					},
					"projectIndex" : 0,
					"source" : ".",
					"targetIndexes" : 
					[
						0
					]
				}
			],
			"name" : "Debug",
			"projects" : 
			[
				{
					"directoryIndexes" : 
					[
						0
					],
					"name" : "qtapms-sim",
					"targetIndexes" : 
					[
						0
					]
				}
			],
			"targets" : 
			[
				{
					"directoryIndex" : 0,
					"id" : "qtapms-sim::@6890427a1f51a3e7e1df",
					"jsonFile" : "target-qtapms-sim-Debug-4822a0646fb5b24078e1.json",
					"name" : "qtapms-sim",
					"projectIndex" : 0
				}
			]
		}
	],
	"kind" : "codemodel",
	"paths" : 
	{
		"build" : "/home/mikey/qtapms-foundations/build",
		"source" : "/home/mikey/qtapms-foundations/sim"
	},
	"version" : 
	{
		"major" : 2,
		"minor" : 6
	}
}
